tickify/__init__.py
tickify/__main__.py
tickify/utils.py
tickify/db/__init__.py
tickify/db/config.py
tickify/db/models.py
tickify/pomodoro/__init__.py
tickify/pomodoro/crud.py
tickify/pomodoro/pomodoro.py
tickify/pomodoro/schemas.py
tickify/pomodoro/test.py
tickify/pomodoro/utils.py
tickify/pomodoro/sounds/long-break-sound.mp3
tickify/pomodoro/sounds/short-break-sound.mp3
tickify/pomodoro/sounds/work-sound.mp3
tickify-1.1.0.dist-info/LICENSE
tickify-1.1.0.dist-info/METADATA
tickify-1.1.0.dist-info/WHEEL
tickify-1.1.0.dist-info/entry_points.txt
tickify-1.1.0.dist-info/top_level.txt
tickify-1.1.0.dist-info/RECORD
